ccsyspath/__init__.py
ccsyspath/paths.py
ccsyspath-1.1.0.dist-info/DESCRIPTION.rst
ccsyspath-1.1.0.dist-info/METADATA
ccsyspath-1.1.0.dist-info/RECORD
ccsyspath-1.1.0.dist-info/WHEEL
ccsyspath-1.1.0.dist-info/metadata.json
ccsyspath-1.1.0.dist-info/top_level.txt
tests/__init__.py
tests/test_paths.py
