Metadata-Version: 2.0
Name: ccsyspath
Version: 1.1.0
Summary: Find the system include paths for clang and gcc C/C++ compilers
Home-page: http://github.com/AndrewWalker/ccsyspath
Author: Andrew Walker
Author-email: walker.ab@gmail.com
License: MIT
Keywords: clang,gcc,compiler
Platform: UNKNOWN
Classifier: Development Status :: 5 - Production/Stable
Classifier: Intended Audience :: Developers
Classifier: License :: OSI Approved :: MIT License
Classifier: Natural Language :: English
Classifier: Programming Language :: Python :: 2
Classifier: Programming Language :: Python :: 2.6
Classifier: Programming Language :: Python :: 2.7
Classifier: Programming Language :: Python :: 3
Classifier: Programming Language :: Python :: 3.3
Classifier: Programming Language :: Python :: 3.4
Classifier: Programming Language :: Python :: 3.5
Classifier: Programming Language :: Python :: Implementation :: CPython
Classifier: Operating System :: OS Independent
